pygaljs/__init__.py
pygaljs/static/.git
pygaljs/static/Gruntfile.coffee
pygaljs/static/README.md
pygaljs/static/bower.json
pygaljs/static/package.json
pygaljs/static/2.0.x/pygal-tooltips.js
pygaljs/static/2.0.x/pygal-tooltips.min.js
pygaljs/static/coffee/pygal-tooltips.coffee
pygaljs/static/javascripts/pygal-tooltips.js
pygaljs/static/javascripts/svg.jquery.js
pygaljs/static/latest/pygal-tooltips.js
pygaljs/static/latest/pygal-tooltips.min.js
pygaljs-1.0.2.dist-info/LICENSE
pygaljs-1.0.2.dist-info/METADATA
pygaljs-1.0.2.dist-info/WHEEL
pygaljs-1.0.2.dist-info/top_level.txt
pygaljs-1.0.2.dist-info/RECORD
