Metadata-Version: 2.1
Name: pygaljs
Version: 1.0.2
Summary: Python package providing assets from https://github.com/Kozea/pygal.js
Home-page: https://github.com/ionelmc/python-pygaljs
Author: Mounier Florian
Author-email: paradoxxx.zero@gmail.com
Maintainer: Ionel Cristian Mărieș
Maintainer-email: contact@ionelmc.ro
License: LGPLv3
Platform: UNKNOWN
Classifier: Development Status :: 5 - Production/Stable
Classifier: Intended Audience :: Developers
Classifier: License :: OSI Approved :: BSD License
Classifier: Operating System :: Unix
Classifier: Operating System :: POSIX
Classifier: Operating System :: Microsoft :: Windows
Classifier: Programming Language :: Python
Classifier: Programming Language :: Python :: 2.6
Classifier: Programming Language :: Python :: 2.7
Classifier: Programming Language :: Python :: 3
Classifier: Programming Language :: Python :: 3.3
Classifier: Programming Language :: Python :: 3.4
Classifier: Programming Language :: Python :: Implementation :: CPython
Classifier: Programming Language :: Python :: Implementation :: PyPy
Classifier: Topic :: Utilities
